half_orm/__init__.py
half_orm/__main__.py
half_orm/cli.py
half_orm/cli_utils.py
half_orm/field.py
half_orm/field_errors.py
half_orm/fkey.py
half_orm/hotest.py
half_orm/model.py
half_orm/model_errors.py
half_orm/null.py
half_orm/pg_meta.py
half_orm/relation.py
half_orm/relation_errors.py
half_orm/relation_factory.py
half_orm/sql_adapter.py
half_orm/transaction.py
half_orm/utils.py
half_orm/version.txt
half_orm-0.17.5.dist-info/AUTHORS
half_orm-0.17.5.dist-info/LICENSE
half_orm-0.17.5.dist-info/METADATA
half_orm-0.17.5.dist-info/WHEEL
half_orm-0.17.5.dist-info/entry_points.txt
half_orm-0.17.5.dist-info/top_level.txt
half_orm-0.17.5.dist-info/RECORD
