Metadata-Version: 2.1
Name: half_orm
Version: 0.17.5
Summary: A simple PostgreSQL to Python mapper.
Home-page: https://github.com/half-orm/half-orm
Author: Joël Maïzi
Author-email: joel.maizi@collorg.org
License: GPLv3
Project-URL: Documentation, https://half-orm.github.io/half-orm/
Project-URL: Source, https://github.com/half-orm/half-orm
Project-URL: Bug Reports, https://github.com/half-orm/half-orm/issues
Classifier: Development Status :: 4 - Beta
Classifier: Operating System :: OS Independent
Classifier: Intended Audience :: Developers
Classifier: Topic :: Database :: Front-Ends
Classifier: Topic :: Software Development :: Libraries :: Application Frameworks
Classifier: License :: OSI Approved :: GNU General Public License v3 (GPLv3)
Classifier: Programming Language :: Python :: 3.7
Classifier: Programming Language :: Python :: 3.8
Classifier: Programming Language :: Python :: 3.9
Classifier: Programming Language :: Python :: 3.10
Classifier: Programming Language :: Python :: 3.11
Classifier: Programming Language :: Python :: 3.12
Classifier: Programming Language :: Python :: 3.13
License-File: LICENSE
License-File: AUTHORS
Requires-Dist: psycopg2-binary
Requires-Dist: click
Requires-Dist: importlib-metadata; python_version < "3.8"
